estimpy/__init__.py
estimpy/analysis.py
estimpy/audio.py
estimpy/cli_player.py
estimpy/cli_visualizer.py
estimpy/export.py
estimpy/metadata.py
estimpy/utils.py
estimpy/visualization.py
estimpy/config/default.yaml
estimpy/config/image-4k-square.yaml
estimpy/config/image-8k-square.yaml
estimpy/config/image-videopreview.yaml
estimpy/config/notitle.yaml
estimpy/config/player-cd028.yaml
estimpy/config/video-120fps.yaml
estimpy/config/video-4k.yaml
estimpy/config/video-60fps.yaml
estimpy/config/video-8k.yaml
estimpy/config/video-av1.yaml
estimpy/config/video-av1_nvenc.yaml
estimpy/config/video-hevc_nvenc.yaml
estimpy/config/video-vp9.yaml
estimpy/player/__init__.py
estimpy/player/audio.py
estimpy/player/player.py
estimpy-1.1.2.dist-info/LICENSE
estimpy-1.1.2.dist-info/METADATA
estimpy-1.1.2.dist-info/WHEEL
estimpy-1.1.2.dist-info/entry_points.txt
estimpy-1.1.2.dist-info/top_level.txt
estimpy-1.1.2.dist-info/RECORD
