Metadata-Version: 2.2
Name: estimpy
Version: 1.1.2
Summary: A package for Estim audio playback and visualization
Author-email: Psynapse <psynapse@psynapse.gay>
License: MIT
Project-URL: Homepage, https://github.com/PsynApps/estimpy
Project-URL: Documentation, https://github.com/PsynApps/estimpy/blob/main/README.md
Project-URL: Source, https://github.com/PsynApps/estimpy
Project-URL: Tracker, https://github.com/PsynApps/estimpy/issues
Project-URL: Changelog, https://github.com/PsynApps/estimpy/blob/main/CHANGELOG.md
Project-URL: Discussions, https://github.com/PsynApps/estimpy/discussions
Project-URL: PyPI, https://pypi.org/project/estimpy/
Classifier: Programming Language :: Python :: 3
Classifier: License :: OSI Approved :: MIT License
Classifier: Operating System :: OS Independent
Requires-Python: >=3.11
License-File: LICENSE
Requires-Dist: audioop-lts; python_version >= "3.13"
Requires-Dist: colorama
Requires-Dist: flatdict
Requires-Dist: matplotlib>=3.7.2
Requires-Dist: mutagen
Requires-Dist: numpy
Requires-Dist: pydub
Requires-Dist: pygame
Requires-Dist: pyqt6
Requires-Dist: pyyaml
Requires-Dist: scipy
Requires-Dist: tqdm
